cheat_ext/__init__.py
cheat_ext/exceptions.py
cheat_ext/info.py
cheat_ext/installer.py
cheat_ext/linker.py
cheat_ext/main.py
cheat_ext/utils.py
cheat_ext/version.py
cheat_ext/tests/__init__.py
cheat_ext/tests/test_info.py
cheat_ext/tests/test_installer.py
cheat_ext/tests/test_linker.py
cheat_ext/tests/test_utils.py
cheat_ext-0.1.dist-info/DESCRIPTION.rst
cheat_ext-0.1.dist-info/METADATA
cheat_ext-0.1.dist-info/RECORD
cheat_ext-0.1.dist-info/WHEEL
cheat_ext-0.1.dist-info/entry_points.txt
cheat_ext-0.1.dist-info/metadata.json
cheat_ext-0.1.dist-info/top_level.txt
