Metadata-Version: 2.0
Name: cheat-ext
Version: 0.1
Summary: Cheat Extension
Home-page: https://github.com/chhsiao90/cheat-ext
Author: chhsiao90
Author-email: chhsiao90@gmail.com
License: MIT
Platform: UNKNOWN
Classifier: License :: OSI Approved :: MIT License
Classifier: Environment :: Console
Classifier: Environment :: Console :: Curses
Classifier: Operating System :: MacOS :: MacOS X
Classifier: Operating System :: POSIX
Classifier: Programming Language :: Python
Classifier: Programming Language :: Python :: 2
Classifier: Programming Language :: Python :: 2.7
Classifier: Programming Language :: Python :: Implementation :: CPython
Classifier: Programming Language :: Python :: Implementation :: PyPy
Requires-Dist: GitPython (==2.1.0)
Provides-Extra: dev
Requires-Dist: mock (==2.0.0); extra == 'dev'
Requires-Dist: tox (==2.5.0); extra == 'dev'
Requires-Dist: pytest (==3.0.4); extra == 'dev'
